Workbook

Sheet Instructions
A1: Retention Campaign ROI Calculator
A3: PURPOSE: Decide how many at-risk customers to target with a retention offer, and whether it pays off.
A5: HOW TO USE
A6: 1. Go to 'ROI_Calculator'.
A7: 2. Change the YELLOW cells: how many risk deciles to target, offer cost per customer, and the offer's save rate.
A8: 3. Read net benefit, ROI and break-even save rate. The sensitivity table shows many scenarios at once.
A10: COLOUR LEGEND
A11: Blue text = data from the Python churn model | Black = formulas | Yellow fill = inputs you can change
A13: KEY ASSUMPTIONS (editable in the Python code):
A14: - Annual revenue per customer = 2% net interest margin x balance + $50 fee income per product held.
A15: - Customers are ranked into 10 risk deciles by the model's churn probability (decile 10 = most likely to leave).
A16: - 'Save rate' = share of would-be leavers the offer keeps. Benefit counted = 1 year of revenue only (conservative).
... A19: Example: target 3 deciles, $50 per customer, 30% save rate -> see the results update on 'ROI_Calculator'.

Sheet ROI_Calculator
A1: Retention Campaign ROI Calculator
A2: Change the yellow cells. Everything else recalculates.
A4: INPUTS
A5: Risk deciles to target (1-10, riskiest first) | B5: 3
A6: Offer cost per targeted customer ($) | B6: 50
A7: Save rate (share of would-be leavers kept) | B7: 0.3
A9: RESULTS
A10: Customers targeted | B10: =SUMIFS(Risk_Deciles!$B$5:$B$14,Risk_Deciles!$A$5:$A$14,">="&(11-$B$5)) -> 3000
A11: % of customer base targeted | B11: =B10/Risk_Deciles!$B$15 -> 0.3
A12: Would-be leavers inside the target group | B12: =SUMIFS(Risk_Deciles!$C$5:$C$14,Risk_Deciles!$A$5:$A$14,">="&(11-$B$5)) -> 1208
A13: % of ALL churners reached | B13: =B12/Risk_Deciles!$C$15 -> 0.66119321
A14: Annual revenue of those leavers ($) | B14: =SUMIFS(Risk_Deciles!$E$5:$E$14,Risk_Deciles!$A$5:$A$14,">="&(11-$B$5)) -> 2307474.6
A15: Revenue saved by the offer ($) | B15: =B14*B7 -> 692242.37
A16: Campaign cost ($) | B16: =B10*B6 -> 150000
A17: NET BENEFIT ($) | B17: =B15-B16 -> 542242.37
A18: ROI (net benefit / cost) | B18: =IFERROR(B17/B16,0) -> 3.6149492
A19: Break-even save rate | B19: =IFERROR(B16/B14,0) -> 0.065006133
A20: Lift vs random targeting | B20: =IFERROR(B13/B11,0) -> 2.2039774
A23: SENSITIVITY: Net benefit ($) at the targeting level above - save rate (down) vs cost per customer (across)
A24: Save rate \ Cost per customer | B24: 25 | C24: 50 | D24: 75 | E24: 100 | F24: 150
A25: 0.1 | B25: =$B$14*$A25-$B$10*B$24 -> 155747.46 | C25: =$B$14*$A25-$B$10*C$24 -> 80747.458 | D25: =$B$14*$A25-$B$10*D$24 -> 5747.4575 | E25: =$B$14*$A25-$B$10*E$24 -> -69252.542 | F25: =$B$14*$A25-$B$10*F$24 -> -219252.54
A26: 0.2 | B26: =$B$14*$A26-$B$10*B$24 -> 386494.92 | C26: =$B$14*$A26-$B$10*C$24 -> 311494.92 | D26: =$B$14*$A26-$B$10*D$24 -> 236494.92 | E26: =$B$14*$A26-$B$10*E$24 -> 161494.92 | F26: =$B$14*$A26-$B$10*F$24 -> 11494.915
A27: 0.3 | B27: =$B$14*$A27-$B$10*B$24 -> 617242.37 | C27: =$B$14*$A27-$B$10*C$24 -> 542242.37 | D27: =$B$14*$A27-$B$10*D$24 -> 467242.37 | E27: =$B$14*$A27-$B$10*E$24 -> 392242.37 | F27: =$B$14*$A27-$B$10*F$24 -> 242242.37
A28: 0.4 | B28: =$B$14*$A28-$B$10*B$24 -> 847989.83 | C28: =$B$14*$A28-$B$10*C$24 -> 772989.83 | D28: =$B$14*$A28-$B$10*D$24 -> 697989.83 | E28: =$B$14*$A28-$B$10*E$24 -> 622989.83 | F28: =$B$14*$A28-$B$10*F$24 -> 472989.83
A29: 0.5 | B29: =$B$14*$A29-$B$10*B$24 -> 1078737.3 | C29: =$B$14*$A29-$B$10*C$24 -> 1003737.3 | D29: =$B$14*$A29-$B$10*D$24 -> 928737.29 | E29: =$B$14*$A29-$B$10*E$24 -> 853737.29 | F29: =$B$14*$A29-$B$10*F$24 -> 703737.29
A31: Values in (brackets) are negative = the campaign loses money at that combination.

Sheet Risk_Deciles
A1: Customers by model risk decile (10 = most likely to churn)
A4: Risk Decile | B4: Customers | C4: Churners (actual) | D4: Annual Revenue ($) | E4: Revenue Lost to Churn ($) | F4: Churn Rate | G4: Share of All Churners
A5: 1 | B5: 1000 | C5: 17 | D5: 966875.42 | E5: 12644.1 | F5: =IFERROR(C5/B5,0) -> 0.017 | G5: =C5/$C$15 -> 0.0093048714
A6: 2 | B6: 1000 | C6: 39 | D6: 1584016.2 | E6: 74774.06 | F6: =IFERROR(C6/B6,0) -> 0.039 | G6: =C6/$C$15 -> 0.02134647
A7: 3 | B7: 1000 | C7: 51 | D7: 1399333.2 | E7: 67086.98 | F7: =IFERROR(C7/B7,0) -> 0.051 | G7: =C7/$C$15 -> 0.027914614
A8: 4 | B8: 1000 | C8: 80 | D8: 1350002.5 | E8: 100050.86 | F8: =IFERROR(C8/B8,0) -> 0.08 | G8: =C8/$C$15 -> 0.04378763
A9: 5 | B9: 1000 | C9: 114 | D9: 1557820.9 | E9: 170415.39 | F9: =IFERROR(C9/B9,0) -> 0.114 | G9: =C9/$C$15 -> 0.062397373
A10: 6 | B10: 1000 | C10: 138 | D10: 1432066.3 | E10: 182584.79 | F10: =IFERROR(C10/B10,0) -> 0.138 | G10: =C10/$C$15 -> 0.075533662
A11: 7 | B11: 1000 | C11: 180 | D11: 1741102.4 | E11: 285397.49 | F11: =IFERROR(C11/B11,0) -> 0.18 | G11: =C11/$C$15 -> 0.098522167
A12: 8 | B12: 1000 | C12: 256 | D12: 1628465.7 | E12: 401686.83 | F12: =IFERROR(C12/B12,0) -> 0.256 | G12: =C12/$C$15 -> 0.14012042
A13: 9 | B13: 1000 | C13: 351 | D13: 1819536.1 | E13: 645175.64 | F13: =IFERROR(C13/B13,0) -> 0.351 | G13: =C13/$C$15 -> 0.19211823
A14: 10 | B14: 1000 | C14: 601 | D14: 2106804.5 | E14: 1260612.1 | F14: =IFERROR(C14/B14,0) -> 0.601 | G14: =C14/$C$15 -> 0.32895457
A15: Total | B15: =SUM(B5:B14) -> 10000 | C15: =SUM(C5:C14) -> 1827 | D15: =SUM(D5:D14) -> 15586023 | E15: =SUM(E5:E14) -> 3200428.2 | F15: =IFERROR(C15/B15,0) -> 0.1827 | G15: =SUM(G5:G14) -> 1

Sheet Segment_Leakage
A1: Revenue leakage by customer segment (balance tier | activity)
A4: Segment | B4: Customers | C4: Churners | D4: Churn Rate | E4: Revenue Lost ($) | F4: Share of Total Loss | G4: Cumulative Share
A5: 100k+ | Inactive | B5: 2198 | C5: 598 | D5: =IFERROR(C5/B5,0) -> 0.27206551 | E5: 1622777 | F5: =E5/$E$11 -> 0.50704996 | G5: =SUM($F$5:F5) -> 0.50704996
A6: 100k+ | Active | B6: 2396 | C6: 357 | D6: =IFERROR(C6/B6,0) -> 0.14899833 | E6: 962859.68 | F6: =E6/$E$11 -> 0.30085339 | G6: =SUM($F$5:F6) -> 0.80790335
A7: <100k | Inactive | B7: 779 | C7: 211 | D7: =IFERROR(C7/B7,0) -> 0.27086008 | E7: 364207.51 | F7: =E7/$E$11 -> 0.11379962 | G7: =SUM($F$5:F7) -> 0.92170297
A8: <100k | Active | B8: 846 | C8: 123 | D8: =IFERROR(C8/B8,0) -> 0.14539007 | E8: 212184.03 | F8: =E8/$E$11 -> 0.066298637 | G8: =SUM($F$5:F8) -> 0.98800161
A9: No balance | Inactive | B9: 1830 | C9: 365 | D9: =IFERROR(C9/B9,0) -> 0.19945355 | E9: 26800 | F9: =E9/$E$11 -> 0.0083738793 | G9: =SUM($F$5:F9) -> 0.99637549
A10: No balance | Active | B10: 1951 | C10: 173 | D10: =IFERROR(C10/B10,0) -> 0.088672476 | E10: 11600 | F10: =E10/$E$11 -> 0.0036245149 | G10: =SUM($F$5:F10) -> 1
A11: Total | B11: =SUM(B5:B10) -> 10000 | C11: =SUM(C5:C10) -> 1827 | D11: =IFERROR(C11/B11,0) -> 0.1827 | E11: =SUM(E5:E10) -> 3200428.2 | F11: =SUM(F5:F10) -> 1
